{
	"NewDataSet": {
		"Table": [
			{
				"sno": "672",
				"catname": "View All",
				"refid": "129",
				"searchid": "indian culture",
				"type": "1",
				"sortid": "0",
				"dispname": "Indian Culture >> View All"
			},
			{
				"sno": "1139",
				"catname": "With People",
				"refid": "129",
				"searchid": "people culture",
				"type": "1",
				"sortid": "4",
				"dispname": "Indian Culture >> With People"
			},
			{
				"sno": "1140",
				"catname": "Without People",
				"refid": "129",
				"searchid": "nobody culture",
				"type": "1",
				"sortid": "7",
				"dispname": "Indian Culture >> Without People"
			},
			{
				"sno": "596",
				"catname": "Art & Sculpture",
				"refid": "129",
				"searchid": "art culture",
				"type": "1",
				"sortid": "13",
				"dispname": "Indian Culture >> Art & Sculpture"
			},
			{
				"sno": "216",
				"catname": "Bengali",
				"refid": "129",
				"searchid": "Bengali",
				"type": "1",
				"sortid": "16",
				"dispname": "Indian Culture >> Bengali"
			},
			{
				"sno": "880",
				"catname": "Brahman",
				"refid": "129",
				"searchid": "Brahman",
				"type": "1",
				"sortid": "19",
				"dispname": "Indian Culture >> Brahman"
			},
			{
				"sno": "87",
				"catname": "Christian",
				"refid": "129",
				"searchid": "Christian",
				"type": "1",
				"sortid": "22",
				"dispname": "Indian Culture >> Christians"
			},
			{
				"sno": "980",
				"catname": "Famous Monuments",
				"refid": "129",
				"searchid": "Ancient",
				"type": "1",
				"sortid": "25",
				"dispname": "Indian Culture >> Famous Monuments"
			},
			{
				"sno": "972",
				"catname": "Festival",
				"refid": "129",
				"searchid": "Festivals",
				"type": "1",
				"sortid": "28",
				"dispname": "Indian Culture >> Festival"
			},
			{
				"sno": "1141",
				"catname": "Grihapravesh",
				"refid": "129",
				"searchid": "Grihapravesh",
				"type": "1",
				"sortid": "31",
				"dispname": "Indian Culture >> Grihapravesh"
			},
			{
				"sno": "874",
				"catname": "Gujarati",
				"refid": "129",
				"searchid": "Gujarati",
				"type": "1",
				"sortid": "34",
				"dispname": "Indian Culture >> Gujarati"
			},
			{
				"sno": "1142",
				"catname": "Handicrafts",
				"refid": "129",
				"searchid": "Handicrafts",
				"type": "1",
				"sortid": "37",
				"dispname": "Indian Culture >> Handicrafts"
			},
			{
				"sno": "873",
				"catname": "Hinduism",
				"refid": "129",
				"searchid": "Hinduism",
				"type": "1",
				"sortid": "40",
				"dispname": "Indian Culture >> Hinduism"
			},
			{
				"sno": "1143",
				"catname": "Indian Dance",
				"refid": "129",
				"searchid": "dance culture",
				"type": "1",
				"sortid": "43",
				"dispname": "Indian Culture >> Indian Dance"
			},
			{
				"sno": "988",
				"catname": "Indian Flag/Patriotism",
				"refid": "129",
				"searchid": "Patriotism",
				"type": "1",
				"sortid": "46",
				"dispname": "Indian Culture >> Indian Flag/Patriotism"
			},
			{
				"sno": "1144",
				"catname": "Indian Music",
				"refid": "129",
				"searchid": "music culture",
				"type": "1",
				"sortid": "49",
				"dispname": "Indian Culture >> Indian Music"
			},
			{
				"sno": "1145",
				"catname": "Jewellery",
				"refid": "129",
				"searchid": "Jewellery",
				"type": "1",
				"sortid": "52",
				"dispname": "Indian Culture >> Jewellery"
			},
			{
				"sno": "877",
				"catname": "Malayalee",
				"refid": "129",
				"searchid": "Malayalee",
				"type": "1",
				"sortid": "55",
				"dispname": "Indian Culture >> Malayalee"
			},
			{
				"sno": "875",
				"catname": "Marathi",
				"refid": "129",
				"searchid": "Marathi",
				"type": "1",
				"sortid": "58",
				"dispname": "Indian Culture >> Marathi"
			},
			{
				"sno": "537",
				"catname": "Marriage/Wedding",
				"refid": "129",
				"searchid": "Marriage",
				"type": "1",
				"sortid": "61",
				"dispname": "Indian Culture >> Marriage/Wedding"
			},
			{
				"sno": "535",
				"catname": "Muslim",
				"refid": "129",
				"searchid": "Muslim",
				"type": "1",
				"sortid": "64",
				"dispname": "Indian Culture >> Muslim"
			},
			{
				"sno": "975",
				"catname": "Namaste/Greeting",
				"refid": "129",
				"searchid": "joined hands welcome",
				"type": "1",
				"sortid": "67",
				"dispname": "Indian Culture >> Namaste/Greeting"
			},
			{
				"sno": "1193",
				"catname": "North Eastern",
				"refid": "129",
				"searchid": "northeast",
				"type": "1",
				"sortid": "68",
				"dispname": "Indian Culture >> North Eastern"
			},
			{
				"sno": "991",
				"catname": "North Indian",
				"refid": "129",
				"searchid": "North Indian people",
				"type": "1",
				"sortid": "70",
				"dispname": "Indian Culture >> North Indian"
			},
			{
				"sno": "88",
				"catname": "Punjabi",
				"refid": "129",
				"searchid": "Punjabi",
				"type": "1",
				"sortid": "73",
				"dispname": "Indian Culture >> Punjabi"
			},
			{
				"sno": "86",
				"catname": "Rajasthani",
				"refid": "129",
				"searchid": "Rajasthani",
				"type": "1",
				"sortid": "76",
				"dispname": "Indian Culture >> Rajasthani"
			},
			{
				"sno": "83",
				"catname": "Religion",
				"refid": "129",
				"searchid": "Religion",
				"type": "1",
				"sortid": "79",
				"dispname": "Indian Culture >> Religion"
			},
			{
				"sno": "1146",
				"catname": "Sikhism",
				"refid": "129",
				"searchid": "Sikhism",
				"type": "1",
				"sortid": "82",
				"dispname": "Indian Culture >> Sikhism"
			},
			{
				"sno": "85",
				"catname": "South Indian",
				"refid": "129",
				"searchid": "South Indian",
				"type": "1",
				"sortid": "85",
				"dispname": "Indian Culture >> South Indian"
			},
			{
				"sno": "1260",
				"catname": "Spirituality",
				"refid": "129",
				"searchid": "Spirituality",
				"type": "1",
				"sortid": "86",
				"dispname": "Indian Culture >> Spirituality"
			},
			{
				"sno": "876",
				"catname": "Tamil/Telugu",
				"refid": "129",
				"searchid": "Tamil",
				"type": "1",
				"sortid": "88",
				"dispname": "Indian Culture >> Tamil/Telugu"
			},
			{
				"sno": "1147",
				"catname": "Temples",
				"refid": "129",
				"searchid": "Temple",
				"type": "1",
				"sortid": "91",
				"dispname": "Indian Culture >> Temples"
			},
			{
				"sno": "1148",
				"catname": "Mosque",
				"refid": "129",
				"searchid": "Mosque",
				"type": "1",
				"sortid": "94",
				"dispname": "Indian Culture >> Mosque"
			},
			{
				"sno": "1149",
				"catname": "Gurudwara",
				"refid": "129",
				"searchid": "Gurudwara",
				"type": "1",
				"sortid": "97",
				"dispname": "Indian Culture >> Gurudwara"
			},
			{
				"sno": "1150",
				"catname": "Church",
				"refid": "129",
				"searchid": "Church",
				"type": "1",
				"sortid": "100",
				"dispname": "Indian Culture >> Church"
			},
			{
				"sno": "1151",
				"catname": "Wearing Saree",
				"refid": "129",
				"searchid": "1xwoman saree",
				"type": "1",
				"sortid": "103",
				"dispname": "Indian Culture >> Wearing Saree"
			},
			{
				"sno": "973",
				"catname": "Worship/Prayer",
				"refid": "129",
				"searchid": "1xpooja",
				"type": "1",
				"sortid": "106",
				"dispname": "Indian Culture >> Worship/Prayer"
			}
		]
	}
}